i2c_master.v
// i2c module for communication w/ ov7670
//
// Timing parameters from i2c datasheet (p48, fast mode)
// -> https://www.nxp.com/docs/en/user-guide/UM10204.pdf
//
// Cross-referenced w/ OV7670 datasheet (p6)
// -> http://web.mit.edu/6.111/www/f2016/tools/OV7670_2006.pdf
//
/* **** INSTANTIATION TEMPLATE ****
	i2c_master 
	#(
	.CLK_FREQ (CLK_FREQ)
	) 
	DUT
	(
    .i_clk         (),
    .i_rstn        (), // async active low rst

    // read/write control 
    .i_wr          (), // write enable
    .i_rd          (), // read enable
    .i_slave_addr  (), // 7-bit slave device addr
    .i_reg_addr    (), // 8-bit register addr
    .i_wdata       (), // 8-bit write data

    // read data out
    .o_rdata       (), // 8-bit read data out

    // status signals
    .o_busy        (), // asserted when r/w in progress
    .o_rdata_valid (), // indicates o_rdata is valid
    .o_nack_slave  (), // NACK on slave address frame
    .o_nack_addr   (), // NACK on register address frame
    .o_nack_data   (), // NACK on data frame

    // bidirectional i2c pins
    .SCL           (), 
    .SDA           ()  
	);

*/
//
`default_nettype none
//
module i2c_master#
	(
		parameter T_CLK = 10
	) 
	(
	input  wire       i_clk,         // 100 MHz clock
	input  wire       i_rstn,        // synchronous active low reset
 	
	input  wire       i_wr,
	input  wire       i_rd,

	input  wire [6:0] i_slave_addr,   // 7'h42 for OV7670
	input  wire [7:0] i_reg_addr,     // register address to read/write
	input  wire [7:0] i_wdata,        // write data
	output reg  [7:0] o_rdata,        // read data

	// Status
	output reg        o_busy,         // asserted when a r/w in progress
	output reg        o_rdata_valid,  // read data valid
	output reg        o_nack_slave,   // NACK on slave address
	output reg        o_nack_addr,    // NACK on register address
	output reg        o_nack_data,    // NACK on data byte

	// SCL and SDA pins
	inout  wire       SCL,
	inout  wire       SDA      
);



// **** SCL and SDA pin setup *****
//
	wire      scl_i;     // SCL in
    reg       scl_o = 1; // SCL out
    
    wire      sda_i;     // SDA in
    reg       sda_o = 1; // SDA out

    assign scl_i = SCL;
    assign SCL = (scl_o) ? 1'bz : 1'b0;

    assign sda_i = SDA;
    assign SDA = (sda_o) ? 1'bz : 1'b0;


// **** Timing Parameters ****
// 
	localparam T_SU_STA = 600/T_CLK;  // START condition setup time  
	localparam T_HD_STA = 600/T_CLK;  // START condition hold time
    localparam T_LOW    = 1300/T_CLK; // SCL low time
	localparam T_HIGH   = 600/T_CLK;  // SCL high time
	localparam T_HD_DAT = 300/T_CLK;  // Data-in hold time
    localparam T_SU_DAT = 100/T_CLK;  // Data-in setup time,
    localparam T_SU_STO = 600/T_CLK;  // STOP condition setup time 

    // timer counter
    localparam TIMER_WIDTH = $clog2(T_LOW);
    reg [TIMER_WIDTH-1:0] timer     = 0;
    reg [TIMER_WIDTH-1:0] nxt_timer = 0;



// **** FSM Registers ****
//
	localparam STATE_INITIAL    = 0,
	           STATE_IDLE       = 1,
	           STATE_START      = 2,
	           STATE_BIT1       = 3,
	           STATE_BIT2       = 4,
	           STATE_BIT3       = 5,
	           STATE_STOP       = 6,
	           STATE_TIMER      = 7; 

	reg [3:0] STATE = STATE_INITIAL;
	reg [3:0] NEXT_STATE;

	reg [3:0] RETURN_STATE;
	reg [3:0] NEXT_RETURN_STATE;


	reg [26:0] sda_txqueue;
	reg [26:0] nxt_sda_txqueue;

	reg [7:0]  read_sr;
	reg [7:0]  nxt_read_sr;

    reg [4:0]  bit_counter;
    reg [4:0]  nxt_bit_counter;
    
    reg        load_r;
    reg        r_wr;
    reg        r_rd;
    reg [6:0]  r_slave_addr;
    reg [7:0]  r_reg_addr;
    reg [7:0]  r_wdata;
     
	reg nxt_scl_o;
	reg nxt_sda_o;

	reg [7:0] nxt_rdata;

	reg nxt_busy;
	reg nxt_rdata_valid;
	reg nxt_nack_slave;
	reg nxt_nack_addr;
	reg nxt_nack_data;

	reg wr_cycle;
	reg nxt_wr_cycle;

	reg repeat_start;
    reg nxt_repeat_start;



// **** Debounce External Inputs ****

    // shift registers initialized to idle values
    reg [3:0] scl_sr = {4{1'b1}};
    reg [3:0] sda_sr = {4{1'b1}};

    reg scl;   // debounced SCL
	reg sda;   // debounced SDA

    always@(posedge i_clk or negedge i_rstn) begin
    	if(!i_rstn) begin
    		scl_sr <= {4{1'b1}};
    		sda_sr <= {4{1'b1}};
    		scl    <= 1;
    		sda    <= 1;
    	end
    	else begin
    		scl_sr <= {scl_sr[2:0], scl_i};
    		sda_sr <= {sda_sr[2:0], sda_i};
    		scl <= (scl_sr == {4{1'b1}});
    		sda <= (sda_sr == {4{1'b1}});
    	end
    end

// **** FSM Next State Logic ****
//
	always@* begin
		nxt_scl_o         = scl_o;          // scl is floating by default           
		nxt_sda_o         = sda_o;          // sda is floating by default
         
        load_r            = 0;
        nxt_wr_cycle      = wr_cycle;
		nxt_sda_txqueue   = sda_txqueue;
        nxt_read_sr       = read_sr;
         
        nxt_rdata         = o_rdata;
		nxt_busy          = o_busy;
		nxt_rdata_valid   = o_rdata_valid;
		nxt_nack_slave    = o_nack_slave;
		nxt_nack_addr     = o_nack_addr;
		nxt_nack_data     = o_nack_data;
  
		nxt_timer         = timer;

		NEXT_STATE        = STATE;
		NEXT_RETURN_STATE = RETURN_STATE;

		case(STATE)

			// initial state
			//     -> T_SU_STA (START setup time)
			//
			//     ___
			// SDA 
			//     ___
			// SCL 
			//
			STATE_INITIAL: begin
				nxt_scl_o         = 1;
				nxt_sda_o         = 1;
				nxt_timer         = T_SU_STA;
				NEXT_STATE        = STATE_TIMER;
				NEXT_RETURN_STATE = STATE_IDLE;
			end
			
		    // idle state; SCL and SDA are high
			STATE_IDLE: begin
				nxt_scl_o      = 1;
				nxt_sda_o      = 1;
				nxt_busy       = 0;
				nxt_nack_slave = 0;
				nxt_nack_addr  = 0;
				nxt_nack_data  = 0;
				if((i_wr || i_rd) && (!o_busy)) begin
					nxt_rdata_valid  = (~i_rd);
					nxt_busy         = 1;
					load_r           = 1;
					nxt_wr_cycle     = 1;
					NEXT_STATE       = STATE_START;
				end
			end

			// START condition; pull SDA low 
			//     -> T_HD_STA (START hold time)
			//     __
			// SDA   \_
			//     ____
			// SCL 
			//
			STATE_START: begin
                nxt_sda_o       = 0;
                nxt_bit_counter = 0;

                // load sda_txqueue with transaction data
                //
				if(i_rd) begin
					// first part of read
					if(wr_cycle) 
						nxt_sda_txqueue = {i_slave_addr, // slave addr         [26:20]     
					                       1'b0,         // write bit          [19]
					                       1'b1,         // release; slave ack [18]
					                       i_reg_addr,   // rd register addr   [17:10]
					                       1'b1,         // release; slave ack [9]
					                       9'b0};        // * not used; repeated start *
					// second part of read
                    else 
                    	nxt_sda_txqueue = {i_slave_addr, // slave addr          [26:20]
					                       1'b1,         // read bit            [19]
					                       1'b1,         // release; slave ack  [18]
					                       8'hff,        // release; read data  [17:10]
					                       1'b1,         // release; master ACK [9]
					                       9'b0};        // * not used; STOP condition *
				end

				// write
				else begin
                    nxt_sda_txqueue = {i_slave_addr, // slave addr         [26:20]
                                       1'b0,         // write bit          [19]
                                       1'b1,         // release; slave ack [18]
                                       i_reg_addr,   // wr register addr   [17:10]
                                       1'b1,         // release; slave ack [9]
                                       i_wdata,      // write data         [8:1]
                                       1'b1};        // release; slave ack [0]
				end

				nxt_timer         = T_HD_STA;
                NEXT_STATE        = (!sda_i) ? STATE_TIMER : STATE_START;
                NEXT_RETURN_STATE = STATE_BIT1;
			end
            
            // Bit Part 1; pull SCL low
            //     -> T_HD_DAT (Data-in Hold Time)
            //     
			// SDA ____
			//     __
			// SCL   \_
			//
            STATE_BIT1: begin
            	nxt_scl_o         = 0;
            	nxt_timer         = T_HD_DAT;
            	NEXT_STATE        = (!scl) ? STATE_TIMER : STATE_BIT1;
            	NEXT_RETURN_STATE = STATE_BIT2;
            end

            // Bit Part 2: SDA transaction
            //     -> T_LOW (SCL low time)
            //        __
			// SDA __/__
			//     
			// SCL _____
			//
            STATE_BIT2: begin
            	nxt_sda_o         = sda_txqueue[26]; 
            	nxt_sda_txqueue   = {sda_txqueue[25:0], 1'b0};
            	nxt_timer         = T_LOW;
            	NEXT_STATE        = STATE_TIMER;
            	NEXT_RETURN_STATE = STATE_BIT3;
            end

            // Bit Part 3: release SCL high
            //      ____
            // SDA /____
            //        __
            // SCL __/
            //
            STATE_BIT3: begin
            	nxt_scl_o       = 1;
            	nxt_timer       = T_HIGH;

            	if(scl) begin
            		nxt_bit_counter = bit_counter + 1;

            		if(bit_counter == 8) begin
            			nxt_nack_slave = sda;
            		end
            		else if ((bit_counter == 17) & wr_cycle) begin
            			nxt_nack_addr = sda;
            		end
            		else if(bit_counter == 26) begin
            			nxt_nack_data = sda;
            		end
            		
            		// for reads:  state transition after second slave ACK
            		// for writes: state transition at end of transmission
            		if( ((bit_counter == 18) & (r_rd)) || (bit_counter == 27)) begin
            			nxt_timer         = T_SU_STO;
            			NEXT_STATE        = STATE_TIMER;
            			NEXT_RETURN_STATE = STATE_STOP;
            		end
            		else begin
            			if((bit_counter != 17) && (r_rd)) begin
            				nxt_read_sr = {read_sr[6:1], sda};
            			end
            			nxt_timer         = T_HIGH;
            			NEXT_STATE        = STATE_TIMER;
            			NEXT_RETURN_STATE = STATE_BIT1;
            		end 
            	end
            end

            // Stop Condition 
            //      __
            // SDA X__\__
            //     ______
            // SCL 
            //
            STATE_STOP: begin
            	sda_o = 1;
            	if(sda) begin
            		// reads
            	    if(r_rd) begin
            	    	// read write register address done
            	    	if(wr_cycle) begin
            	    		if(r_rd) begin
            	    			nxt_timer = T_SU_STA - T_SU_STO;
            	    		end
            	    		else begin
            	    			nxt_timer = T_SU_STA;
            	    		end
            	    		NEXT_RETURN_STATE = STATE_START;
            	    	end
            	    	// read received
            	    	else begin
            	    		nxt_rdata         = read_sr;
            	    		nxt_rdata_valid   = 1;
            	    		nxt_timer         = T_SU_STA;
            	    		NEXT_RETURN_STATE = STATE_IDLE;
            	    	end
            	    	nxt_wr_cycle = 0;
            	    	NEXT_STATE   = STATE_TIMER;
            	    end

            	    // writes
            	    else begin
    					nxt_rdata_valid   = 0;
    					nxt_timer         = T_SU_STA;
    					NEXT_STATE        = STATE_TIMER;
    					NEXT_RETURN_STATE = STATE_IDLE;
            	    end
                end
            end

            STATE_TIMER: begin
            	if(timer == 0) begin
            		NEXT_STATE = RETURN_STATE;
            	end
            	else begin
            		nxt_timer = timer - 1;
            	end
            end

		endcase 
	end

// **** FSM Registers ****
//
	always@(posedge i_clk or negedge i_rstn) begin
		if(!i_rstn) begin
			o_rdata       <= 8'h0;
			o_busy        <= 0;
			o_rdata_valid <= 0;
			o_nack_slave  <= 0;
			o_nack_addr   <= 0;
			o_nack_data   <= 0;

			scl_o         <= 1;
			sda_o         <= 1;

			sda_txqueue   <= {27{1'b1}};
			read_sr       <= 8'h0;
			bit_counter   <= 5'h0;

			wr_cycle      <= 0;
			repeat_start  <= 0;

			r_wr          <= 0;
            r_rd          <= 0;
            r_slave_addr  <= 0;
            r_reg_addr    <= 0;
            r_wdata       <= 0;

            timer         <= 0;

			STATE         <= STATE_INITIAL;
			RETURN_STATE  <= STATE_IDLE;
		end
		else begin
			o_rdata       <= nxt_rdata;
			o_busy        <= nxt_busy;
			o_rdata_valid <= nxt_rdata_valid;
			o_nack_slave  <= nxt_nack_slave;
			o_nack_addr   <= nxt_nack_addr;
			o_nack_data   <= nxt_nack_data;

			scl_o         <= nxt_scl_o;
			sda_o         <= nxt_sda_o;

			sda_txqueue   <= nxt_sda_txqueue;
			read_sr       <= nxt_read_sr;
			bit_counter   <= nxt_bit_counter;

			wr_cycle      <= nxt_wr_cycle;
			repeat_start  <= nxt_repeat_start;

			timer         <= nxt_timer;

			if(load_r) begin
				r_wr         <= i_wr;
				r_rd         <= i_rd;
				r_slave_addr <= i_slave_addr;
				r_reg_addr   <= i_reg_addr;
				r_wdata      <= i_wdata;
			end

			STATE         <= NEXT_STATE;
			RETURN_STATE  <= NEXT_RETURN_STATE;
		end
	end



endmodule

i2c_master_tb.v
//
//
module i2c_master_tb();

    reg        i_clk = 0;
    reg        i_rstn;

    reg        i_wr;
    reg        i_rd;
    reg  [7:0] i_reg_addr;
    reg  [7:0] i_wdata;

    wire [7:0] o_rdata;

    wire       o_busy;
    wire       o_rdata_valid;
    wire [2:0] nack_status;

    wire scl, sda;

    pullup(scl);
    pullup(sda);

    always#(5) i_clk = ~i_clk;

    parameter T_CLK = 10;

    i2c_master 
    #(
    .T_CLK (T_CLK)
    ) 
    DUT
    (
    .i_clk         (i_clk          ), 
    .i_rstn        (i_rstn         ), // async active low rst
 
    // read/write control  
    .i_wr          (i_wr           ), // write enable
    .i_rd          (i_rd           ), // read enable
    .i_slave_addr  (7'h42          ), // 7-bit slave device addr
    .i_reg_addr    (i_reg_addr     ), // 8-bit register addr
    .i_wdata       (i_wdata        ), // 8-bit write data
 
    // read data out 
    .o_rdata       (o_rdata        ), // 8-bit read data out

    // status signals
    .o_busy        (o_busy         ), // asserted when r/w in progress
    .o_rdata_valid (o_rdata_valid  ), // indicates o_rdata is valid
    .o_nack_slave  (nack_status[2] ), // NACK on slave address frame
    .o_nack_addr   (nack_status[1] ), // NACK on register address frame
    .o_nack_data   (nack_status[0] ), // NACK on data frame

    // bidirectional i2c pins
    .SCL           (scl            ), 
    .SDA           (sda            )  
    );

    initial begin
       $dumpfile("i2c_master_tb.vcd");
       $dumpvars(0, i2c_master_tb);
    end

    initial begin
        i_rstn     = 0;
        i_wr       = 0;
        i_rd       = 0;
        i_reg_addr = 0;
        i_wdata    = 0;

        #100;

        @(posedge i_clk) begin
            i_rstn  <= 1;
        end

        // attempt to write during initializations state
        // -> should be ignored
        @(posedge i_clk) begin
            i_wr       <= 1;
            i_reg_addr <= 8'h12;
            i_wdata    <= 8'h80;
        end

        // wait out initialization state
        #700;

        // write 0x80 to register 0x12
        @(posedge i_clk) begin
            i_wr       <= 1;
            i_reg_addr <= 8'h12;
            i_wdata    <= 8'h80;
        end

        @(posedge i_clk) begin
            i_wr       <= 0;
            i_reg_addr <= 0;
            i_wdata    <= 0;
        end

        #500_000;
        $finish;
    end

endmodule

i2c_master_tb.vcd
$date
	Sat Aug 21 20:51:30 2021
$end
$version
	Icarus Verilog
$end
$timescale
	1s
$end
$scope module i2c_master_tb $end
$var wire 1 ! scl $end
$var wire 1 " sda $end
$var wire 1 # o_rdata_valid $end
$var wire 8 $ o_rdata [7:0] $end
$var wire 1 % o_busy $end
$var wire 3 & nack_status [2:0] $end
$var reg 1 ' i_clk $end
$var reg 1 ( i_rd $end
$var reg 8 ) i_reg_addr [7:0] $end
$var reg 1 * i_rstn $end
$var reg 8 + i_wdata [7:0] $end
$var reg 1 , i_wr $end
$scope module DUT $end
$var wire 1 ! SCL $end
$var wire 1 " SDA $end
$var wire 1 ' i_clk $end
$var wire 1 ( i_rd $end
$var wire 8 - i_reg_addr [7:0] $end
$var wire 1 * i_rstn $end
$var wire 7 . i_slave_addr [6:0] $end
$var wire 8 / i_wdata [7:0] $end
$var wire 1 , i_wr $end
$var wire 1 0 scl_i $end
$var wire 1 1 sda_i $end
$var reg 4 2 NEXT_RETURN_STATE [3:0] $end
$var reg 4 3 NEXT_STATE [3:0] $end
$var reg 4 4 RETURN_STATE [3:0] $end
$var reg 4 5 STATE [3:0] $end
$var reg 5 6 bit_counter [4:0] $end
$var reg 1 7 load_r $end
$var reg 5 8 nxt_bit_counter [4:0] $end
$var reg 1 9 nxt_busy $end
$var reg 1 : nxt_nack_addr $end
$var reg 1 ; nxt_nack_data $end
$var reg 1 < nxt_nack_slave $end
$var reg 8 = nxt_rdata [7:0] $end
$var reg 1 > nxt_rdata_valid $end
$var reg 8 ? nxt_read_sr [7:0] $end
$var reg 1 @ nxt_repeat_start $end
$var reg 1 A nxt_scl_o $end
$var reg 1 B nxt_sda_o $end
$var reg 27 C nxt_sda_txqueue [26:0] $end
$var reg 8 D nxt_timer [7:0] $end
$var reg 1 E nxt_wr_cycle $end
$var reg 1 % o_busy $end
$var reg 1 F o_nack_addr $end
$var reg 1 G o_nack_data $end
$var reg 1 H o_nack_slave $end
$var reg 8 I o_rdata [7:0] $end
$var reg 1 # o_rdata_valid $end
$var reg 1 J r_rd $end
$var reg 8 K r_reg_addr [7:0] $end
$var reg 7 L r_slave_addr [6:0] $end
$var reg 8 M r_wdata [7:0] $end
$var reg 1 N r_wr $end
$var reg 8 O read_sr [7:0] $end
$var reg 1 P repeat_start $end
$var reg 1 Q scl $end
$var reg 1 R scl_o $end
$var reg 4 S scl_sr [3:0] $end
$var reg 1 T sda $end
$var reg 1 U sda_o $end
$var reg 4 V sda_sr [3:0] $end
$var reg 27 W sda_txqueue [26:0] $end
$var reg 8 X timer [7:0] $end
$var reg 1 Y wr_cycle $end
$upscope $end
$upscope $end
$enddefinitions $end
#0
$dumpvars
0Y
b0 X
b111111111111111111111111111 W
b1111 V
1U
1T
b1111 S
1R
1Q
0P
b0 O
0N
b0 M
b0 L
b0 K
0J
b0 I
0H
0G
0F
0E
b111100 D
b111111111111111111111111111 C
1B
1A
x@
b0 ?
0>
b0 =
0<
0;
0:
09
bx 8
07
b0 6
b0 5
b1 4
b111 3
b1 2
11
10
b0 /
b1000010 .
b0 -
0,
b0 +
0*
b0 )
0(
0'
b0 &
0%
b0 $
0#
1"
1!
$end
#5
1'
#10
0'
#15
1'
#20
0'
#25
1'
#30
0'
#35
1'
#40
0'
#45
1'
#50
0'
#55
1'
#60
0'
#65
1'
#70
0'
#75
1'
#80
0'
#85
1'
#90
0'
#95
1'
#100
0'
#105
1*
1'
#110
0'
#115
b111011 D
b111 5
b111100 X
xP
bx 6
b10000000 +
b10000000 /
b10010 )
b10010 -
1,
1'
#120
0'
#125
b111010 D
b111011 X
1'
#130
0'
#135
b111001 D
b111010 X
1'
#140
0'
#145
b111000 D
b111001 X
1'
#150
0'
#155
b110111 D
b111000 X
1'
#160
0'
#165
b110110 D
b110111 X
1'
#170
0'
#175
b110101 D
b110110 X
1'
#180
0'
#185
b110100 D
b110101 X
1'
#190
0'
#195
b110011 D
b110100 X
1'
#200
0'
#205
b110010 D
b110011 X
1'
#210
0'
#215
b110001 D
b110010 X
1'
#220
0'
#225
b110000 D
b110001 X
1'
#230
0'
#235
b101111 D
b110000 X
1'
#240
0'
#245
b101110 D
b101111 X
1'
#250
0'
#255
b101101 D
b101110 X
1'
#260
0'
#265
b101100 D
b101101 X
1'
#270
0'
#275
b101011 D
b101100 X
1'
#280
0'
#285
b101010 D
b101011 X
1'
#290
0'
#295
b101001 D
b101010 X
1'
#300
0'
#305
b101000 D
b101001 X
1'
#310
0'
#315
b100111 D
b101000 X
1'
#320
0'
#325
b100110 D
b100111 X
1'
#330
0'
#335
b100101 D
b100110 X
1'
#340
0'
#345
b100100 D
b100101 X
1'
#350
0'
#355
b100011 D
b100100 X
1'
#360
0'
#365
b100010 D
b100011 X
1'
#370
0'
#375
b100001 D
b100010 X
1'
#380
0'
#385
b100000 D
b100001 X
1'
#390
0'
#395
b11111 D
b100000 X
1'
#400
0'
#405
b11110 D
b11111 X
1'
#410
0'
#415
b11101 D
b11110 X
1'
#420
0'
#425
b11100 D
b11101 X
1'
#430
0'
#435
b11011 D
b11100 X
1'
#440
0'
#445
b11010 D
b11011 X
1'
#450
0'
#455
b11001 D
b11010 X
1'
#460
0'
#465
b11000 D
b11001 X
1'
#470
0'
#475
b10111 D
b11000 X
1'
#480
0'
#485
b10110 D
b10111 X
1'
#490
0'
#495
b10101 D
b10110 X
1'
#500
0'
#505
b10100 D
b10101 X
1'
#510
0'
#515
b10011 D
b10100 X
1'
#520
0'
#525
b10010 D
b10011 X
1'
#530
0'
#535
b10001 D
b10010 X
1'
#540
0'
#545
b10000 D
b10001 X
1'
#550
0'
#555
b1111 D
b10000 X
1'
#560
0'
#565
b1110 D
b1111 X
1'
#570
0'
#575
b1101 D
b1110 X
1'
#580
0'
#585
b1100 D
b1101 X
1'
#590
0'
#595
b1011 D
b1100 X
1'
#600
0'
#605
b1010 D
b1011 X
1'
#610
0'
#615
b1001 D
b1010 X
1'
#620
0'
#625
b1000 D
b1001 X
1'
#630
0'
#635
b111 D
b1000 X
1'
#640
0'
#645
b110 D
b111 X
1'
#650
0'
#655
b101 D
b110 X
1'
#660
0'
#665
b100 D
b101 X
1'
#670
0'
#675
b11 D
b100 X
1'
#680
0'
#685
b10 D
b11 X
1'
#690
0'
#695
b1 D
b10 X
1'
#700
0'
#705
b0 D
b1 X
1'
#710
0'
#715
b1 3
b0 X
1'
#720
0'
#725
b10 3
1E
17
19
1>
b1 5
1'
#730
0'
#735
b11 2
b111100 D
b100001001000100101100000001 C
b0 8
0B
07
b10 5
b10000000 M
b10010 K
b1000010 L
1N
1Y
1#
1%
1'
#740
0'
#745
b111 3
01
0"
b11 4
b111100 X
b0 6
b100001001000100101100000001 W
0U
1'
#750
0'
#755
b111011 D
b1110 V
b111 5
1'
#760
0'
#765
b111010 D
b111011 X
0T
b1100 V
1'
#770
0'
#775
b111001 D
b1000 V
b111010 X
1'
#780
0'
#785
b111000 D
b111001 X
b0 V
1'
#790
0'
#795
b110111 D
b111000 X
1'
#800
0'
#805
b110110 D
b110111 X
1'
#810
0'
#815
b110101 D
b110110 X
1'
#820
0'
#825
b110100 D
b110101 X
b0 +
b0 /
b0 )
b0 -
0,
1'
#830
0'
#835
b110011 D
b110100 X
1'
#840
0'
#845
b110010 D
b110011 X
1'
#850
0'
#855
b110001 D
b110010 X
1'
#860
0'
#865
b110000 D
b110001 X
1'
#870
0'
#875
b101111 D
b110000 X
1'
#880
0'
#885
b101110 D
b101111 X
1'
#890
0'
#895
b101101 D
b101110 X
1'
#900
0'
#905
b101100 D
b101101 X
1'
#910
0'
#915
b101011 D
b101100 X
1'
#920
0'
#925
b101010 D
b101011 X
1'
#930
0'
#935
b101001 D
b101010 X
1'
#940
0'
#945
b101000 D
b101001 X
1'
#950
0'
#955
b100111 D
b101000 X
1'
#960
0'
#965
b100110 D
b100111 X
1'
#970
0'
#975
b100101 D
b100110 X
1'
#980
0'
#985
b100100 D
b100101 X
1'
#990
0'
#995
b100011 D
b100100 X
1'
#1000
0'
#1005
b100010 D
b100011 X
1'
#1010
0'
#1015
b100001 D
b100010 X
1'
#1020
0'
#1025
b100000 D
b100001 X
1'
#1030
0'
#1035
b11111 D
b100000 X
1'
#1040
0'
#1045
b11110 D
b11111 X
1'
#1050
0'
#1055
b11101 D
b11110 X
1'
#1060
0'
#1065
b11100 D
b11101 X
1'
#1070
0'
#1075
b11011 D
b11100 X
1'
#1080
0'
#1085
b11010 D
b11011 X
1'
#1090
0'
#1095
b11001 D
b11010 X
1'
#1100
0'
#1105
b11000 D
b11001 X
1'
#1110
0'
#1115
b10111 D
b11000 X
1'
#1120
0'
#1125
b10110 D
b10111 X
1'
#1130
0'
#1135
b10101 D
b10110 X
1'
#1140
0'
#1145
b10100 D
b10101 X
1'
#1150
0'
#1155
b10011 D
b10100 X
1'
#1160
0'
#1165
b10010 D
b10011 X
1'
#1170
0'
#1175
b10001 D
b10010 X
1'
#1180
0'
#1185
b10000 D
b10001 X
1'
#1190
0'
#1195
b1111 D
b10000 X
1'
#1200
0'
#1205
b1110 D
b1111 X
1'
#1210
0'
#1215
b1101 D
b1110 X
1'
#1220
0'
#1225
b1100 D
b1101 X
1'
#1230
0'
#1235
b1011 D
b1100 X
1'
#1240
0'
#1245
b1010 D
b1011 X
1'
#1250
0'
#1255
b1001 D
b1010 X
1'
#1260
0'
#1265
b1000 D
b1001 X
1'
#1270
0'
#1275
b111 D
b1000 X
1'
#1280
0'
#1285
b110 D
b111 X
1'
#1290
0'
#1295
b101 D
b110 X
1'
#1300
0'
#1305
b100 D
b101 X
1'
#1310
0'
#1315
b11 D
b100 X
1'
#1320
0'
#1325
b10 D
b11 X
1'
#1330
0'
#1335
b1 D
b10 X
1'
#1340
0'
#1345
b0 D
b1 X
1'
#1350
0'
#1355
b11 3
b0 X
1'
#1360
0'
#1365
b100 2
b11110 D
0A
b11 5
1'
#1370
0'
#1375
00
0!
b100 4
b11110 X
0R
1'
#1380
0'
#1385
b1110 S
1'
#1390
0'
#1395
b111 3
0Q
b1100 S
1'
#1400
0'
#1405
b11101 D
b111 5
b1000 S
1'
#1410
0'
#1415
b11100 D
b0 S
b11101 X
1'
#1420
0'
#1425
b11011 D
b11100 X
1'
#1430
0'
#1435
b11010 D
b11011 X
1'
#1440
0'
#1445
b11001 D
b11010 X
1'
#1450
0'
#1455
b11000 D
b11001 X
1'
#1460
0'
#1465
b10111 D
b11000 X
1'
#1470
0'
#1475
b10110 D
b10111 X
1'
#1480
0'
#1485
b10101 D
b10110 X
1'
#1490
0'
#1495
b10100 D
b10101 X
1'
#1500
0'
#1505
b10011 D
b10100 X
1'
#1510
0'
#1515
b10010 D
b10011 X
1'
#1520
0'
#1525
b10001 D
b10010 X
1'
#1530
0'
#1535
b10000 D
b10001 X
1'
#1540
0'
#1545
b1111 D
b10000 X
1'
#1550
0'
#1555
b1110 D
b1111 X
1'
#1560
0'
#1565
b1101 D
b1110 X
1'
#1570
0'
#1575
b1100 D
b1101 X
1'
#1580
0'
#1585
b1011 D
b1100 X
1'
#1590
0'
#1595
b1010 D
b1011 X
1'
#1600
0'
#1605
b1001 D
b1010 X
1'
#1610
0'
#1615
b1000 D
b1001 X
1'
#1620
0'
#1625
b111 D
b1000 X
1'
#1630
0'
#1635
b110 D
b111 X
1'
#1640
0'
#1645
b101 D
b110 X
1'
#1650
0'
#1655
b100 D
b101 X
1'
#1660
0'
#1665
b11 D
b100 X
1'
#1670
0'
#1675
b10 D
b11 X
1'
#1680
0'
#1685
b1 D
b10 X
1'
#1690
0'
#1695
b0 D
b1 X
1'
#1700
0'
#1705
b100 3
b0 X
1'
#1710
0'
#1715
b101 2
b111 3
b10000010 D
b10010001001011000000010 C
1B
b100 5
1'
#1720
0'
#1725
b10000001 D
11
1"
b101 4
b111 5
b10000010 X
b10010001001011000000010 W
1U
1'
#1730
0'
#1735
b10000000 D
b1 V
b10000001 X
1'
#1740
0'
#1745
b1111111 D
b10000000 X
b11 V
1'
#1750
0'
#1755
b1111110 D
b111 V
b1111111 X
1'
#1760
0'
#1765
b1111101 D
b1111110 X
b1111 V
1'
#1770
0'
#1775
b1111100 D
1T
b1111101 X
1'
#1780
0'
#1785
b1111011 D
b1111100 X
1'
#1790
0'
#1795
b1111010 D
b1111011 X
1'
#1800
0'
#1805
b1111001 D
b1111010 X
1'
#1810
0'
#1815
b1111000 D
b1111001 X
1'
#1820
0'
#1825
b1110111 D
b1111000 X
1'
#1830
0'
#1835
b1110110 D
b1110111 X
1'
#1840
0'
#1845
b1110101 D
b1110110 X
1'
#1850
0'
#1855
b1110100 D
b1110101 X
1'
#1860
0'
#1865
b1110011 D
b1110100 X
1'
#1870
0'
#1875
b1110010 D
b1110011 X
1'
#1880
0'
#1885
b1110001 D
b1110010 X
1'
#1890
0'
#1895
b1110000 D
b1110001 X
1'
#1900
0'
#1905
b1101111 D
b1110000 X
1'
#1910
0'
#1915
b1101110 D
b1101111 X
1'
#1920
0'
#1925
b1101101 D
b1101110 X
1'
#1930
0'
#1935
b1101100 D
b1101101 X
1'
#1940
0'
#1945
b1101011 D
b1101100 X
1'
#1950
0'
#1955
b1101010 D
b1101011 X
1'
#1960
0'
#1965
b1101001 D
b1101010 X
1'
#1970
0'
#1975
b1101000 D
b1101001 X
1'
#1980
0'
#1985
b1100111 D
b1101000 X
1'
#1990
0'
#1995
b1100110 D
b1100111 X
1'
#2000
0'
#2005
b1100101 D
b1100110 X
1'
#2010
0'
#2015
b1100100 D
b1100101 X
1'
#2020
0'
#2025
b1100011 D
b1100100 X
1'
#2030
0'
#2035
b1100010 D
b1100011 X
1'
#2040
0'
#2045
b1100001 D
b1100010 X
1'
#2050
0'
#2055
b1100000 D
b1100001 X
1'
#2060
0'
#2065
b1011111 D
b1100000 X
1'
#2070
0'
#2075
b1011110 D
b1011111 X
1'
#2080
0'
#2085
b1011101 D
b1011110 X
1'
#2090
0'
#2095
b1011100 D
b1011101 X
1'
#2100
0'
#2105
b1011011 D
b1011100 X
1'
#2110
0'
#2115
b1011010 D
b1011011 X
1'
#2120
0'
#2125
b1011001 D
b1011010 X
1'
#2130
0'
#2135
b1011000 D
b1011001 X
1'
#2140
0'
#2145
b1010111 D
b1011000 X
1'
#2150
0'
#2155
b1010110 D
b1010111 X
1'
#2160
0'
#2165
b1010101 D
b1010110 X
1'
#2170
0'
#2175
b1010100 D
b1010101 X
1'
#2180
0'
#2185
b1010011 D
b1010100 X
1'
#2190
0'
#2195
b1010010 D
b1010011 X
1'
#2200
0'
#2205
b1010001 D
b1010010 X
1'
#2210
0'
#2215
b1010000 D
b1010001 X
1'
#2220
0'
#2225
b1001111 D
b1010000 X
1'
#2230
0'
#2235
b1001110 D
b1001111 X
1'
#2240
0'
#2245
b1001101 D
b1001110 X
1'
#2250
0'
#2255
b1001100 D
b1001101 X
1'
#2260
0'
#2265
b1001011 D
b1001100 X
1'
#2270
0'
#2275
b1001010 D
b1001011 X
1'
#2280
0'
#2285
b1001001 D
b1001010 X
1'
#2290
0'
#2295
b1001000 D
b1001001 X
1'
#2300
0'
#2305
b1000111 D
b1001000 X
1'
#2310
0'
#2315
b1000110 D
b1000111 X
1'
#2320
0'
#2325
b1000101 D
b1000110 X
1'
#2330
0'
#2335
b1000100 D
b1000101 X
1'
#2340
0'
#2345
b1000011 D
b1000100 X
1'
#2350
0'
#2355
b1000010 D
b1000011 X
1'
#2360
0'
#2365
b1000001 D
b1000010 X
1'
#2370
0'
#2375
b1000000 D
b1000001 X
1'
#2380
0'
#2385
b111111 D
b1000000 X
1'
#2390
0'
#2395
b111110 D
b111111 X
1'
#2400
0'
